hexwordify
