Metadata-Version: 1.0
Name: hexwordify
Version: 0.0.3
Summary: Turn hexadecimal strings to readable words.
Home-page: UNKNOWN
Author: Dimitris Zervas
Author-email: dzervas@dzervas.gr
License: UNKNOWN
Platform: UNKNOWN
